[
  {
    "Season": "2015-16",
    "Lg": "NHL",
    "Team": "St. Louis Blues*",
    "GP": 82,
    "W": 49,
    "L": 24,
    "T": "",
    "OL": 9,
    "PTS": 107,
    "PTS%": 0.652,
    "SRS": 0.28,
    "SOS": 0,
    "Finish": "2nd",
    "Playoffs": "Lost NHL Conference Finals",
    "Coaches": "K. Hitchcock (49-24-9)"
  },
  {
    "Season": "2014-15",
    "Lg": "NHL",
    "Team": "St. Louis Blues*",
    "GP": 82,
    "W": 51,
    "L": 24,
    "T": "",
    "OL": 7,
    "PTS": 109,
    "PTS%": 0.665,
    "SRS": 0.59,
    "SOS": 0.02,
    "Finish": "1st",
    "Playoffs": "Lost NHL First Round",
    "Coaches": "K. Hitchcock (51-24-7)"
  },
  {
    "Season": "2013-14",
    "Lg": "NHL",
    "Team": "St. Louis Blues*",
    "GP": 82,
    "W": 52,
    "L": 23,
    "T": "",
    "OL": 7,
    "PTS": 111,
    "PTS%": 0.677,
    "SRS": 0.71,
    "SOS": 0.01,
    "Finish": "2nd",
    "Playoffs": "Lost NHL First Round",
    "Coaches": "K. Hitchcock (52-23-7)"
  },
  {
    "Season": "2012-13",
    "Lg": "NHL",
    "Team": "St. Louis Blues*",
    "GP": 48,
    "W": 29,
    "L": 17,
    "T": "",
    "OL": 2,
    "PTS": 60,
    "PTS%": 0.625,
    "SRS": 0.31,
    "SOS": 0.02,
    "Finish": "2nd",
    "Playoffs": "Lost NHL Conference Quarter-Finals",
    "Coaches": "K. Hitchcock (29-17-2)"
  },
  {
    "Season": "2011-12",
    "Lg": "NHL",
    "Team": "St. Louis Blues*",
    "GP": 82,
    "W": 49,
    "L": 22,
    "T": "",
    "OL": 11,
    "PTS": 109,
    "PTS%": 0.665,
    "SRS": 0.54,
    "SOS": -0.01,
    "Finish": "1st",
    "Playoffs": "Lost NHL Conference Semi-Finals",
    "Coaches": "D. Payne (6-7-0) K. Hitchcock (43-15-11)"
  },
  {
    "Season": "2010-11",
    "Lg": "NHL",
    "Team": "St. Louis Blues",
    "GP": 82,
    "W": 38,
    "L": 33,
    "T": "",
    "OL": 11,
    "PTS": 87,
    "PTS%": 0.53,
    "SRS": 0.11,
    "SOS": 0.04,
    "Finish": "4th",
    "Playoffs": "",
    "Coaches": "D. Payne (38-33-11)"
  },
  {
    "Season": "2009-10",
    "Lg": "NHL",
    "Team": "St. Louis Blues",
    "GP": 82,
    "W": 40,
    "L": 32,
    "T": "",
    "OL": 10,
    "PTS": 90,
    "PTS%": 0.549,
    "SRS": 0.08,
    "SOS": 0.06,
    "Finish": "4th",
    "Playoffs": "",
    "Coaches": "A. Murray (17-17-6) D. Payne (23-15-4)"
  },
  {
    "Season": "2008-09",
    "Lg": "NHL",
    "Team": "St. Louis Blues*",
    "GP": 82,
    "W": 41,
    "L": 31,
    "T": "",
    "OL": 10,
    "PTS": 92,
    "PTS%": 0.561,
    "SRS": 0.05,
    "SOS": 0.05,
    "Finish": "3rd",
    "Playoffs": "Lost NHL Conference Quarter-Finals",
    "Coaches": "A. Murray (41-31-10)"
  },
  {
    "Season": "2007-08",
    "Lg": "NHL",
    "Team": "St. Louis Blues",
    "GP": 82,
    "W": 33,
    "L": 36,
    "T": "",
    "OL": 13,
    "PTS": 79,
    "PTS%": 0.482,
    "SRS": -0.24,
    "SOS": 0.16,
    "Finish": "5th",
    "Playoffs": "",
    "Coaches": "A. Murray (33-36-13)"
  },
  {
    "Season": "2006-07",
    "Lg": "NHL",
    "Team": "St. Louis Blues",
    "GP": 82,
    "W": 34,
    "L": 35,
    "T": "",
    "OL": 13,
    "PTS": 81,
    "PTS%": 0.494,
    "SRS": -0.33,
    "SOS": 0.15,
    "Finish": "3rd",
    "Playoffs": "",
    "Coaches": "M. Kitchen (7-17-4) A. Murray (27-18-9)"
  },
  {
    "Season": "2005-06",
    "Lg": "NHL",
    "Team": "St. Louis Blues",
    "GP": 82,
    "W": 21,
    "L": 46,
    "T": "",
    "OL": 15,
    "PTS": 57,
    "PTS%": 0.348,
    "SRS": -1.09,
    "SOS": 0.07,
    "Finish": "5th",
    "Playoffs": "",
    "Coaches": "M. Kitchen (21-46-15)"
  },
  {
    "Season": "2003-04",
    "Lg": "NHL",
    "Team": "St. Louis Blues*",
    "GP": 82,
    "W": 39,
    "L": 30,
    "T": 11,
    "OL": 2,
    "PTS": 91,
    "PTS%": 0.555,
    "SRS": -0.09,
    "SOS": -0.01,
    "Finish": "2nd",
    "Playoffs": "Lost NHL Conference Quarter-Finals",
    "Coaches": "J. Quenneville (29-23-7-2) M. Kitchen (10-7-4-0)"
  },
  {
    "Season": "2002-03",
    "Lg": "NHL",
    "Team": "St. Louis Blues*",
    "GP": 82,
    "W": 41,
    "L": 24,
    "T": 11,
    "OL": 6,
    "PTS": 99,
    "PTS%": 0.604,
    "SRS": 0.43,
    "SOS": 0.05,
    "Finish": "2nd",
    "Playoffs": "Lost NHL Conference Quarter-Finals",
    "Coaches": "J. Quenneville (41-24-11-6)"
  },
  {
    "Season": "2001-02",
    "Lg": "NHL",
    "Team": "St. Louis Blues*",
    "GP": 82,
    "W": 43,
    "L": 27,
    "T": 8,
    "OL": 4,
    "PTS": 98,
    "PTS%": 0.598,
    "SRS": 0.54,
    "SOS": 0.07,
    "Finish": "2nd",
    "Playoffs": "Lost NHL Conference Semi-Finals",
    "Coaches": "J. Quenneville (43-27-8-4)"
  },
  {
    "Season": "2000-01",
    "Lg": "NHL",
    "Team": "St. Louis Blues*",
    "GP": 82,
    "W": 43,
    "L": 22,
    "T": 12,
    "OL": 5,
    "PTS": 103,
    "PTS%": 0.628,
    "SRS": 0.67,
    "SOS": 0.01,
    "Finish": "2nd",
    "Playoffs": "Lost NHL Conference Finals",
    "Coaches": "J. Quenneville (43-22-12-5)"
  },
  {
    "Season": "1999-00",
    "Lg": "NHL",
    "Team": "St. Louis Blues*",
    "GP": 82,
    "W": 51,
    "L": 19,
    "T": 11,
    "OL": 1,
    "PTS": 114,
    "PTS%": 0.695,
    "SRS": 1.08,
    "SOS": 0.07,
    "Finish": "1st",
    "Playoffs": "Lost NHL Conference Quarter-Finals",
    "Coaches": "J. Quenneville (51-19-11-1)"
  },
  {
    "Season": "1998-99",
    "Lg": "NHL",
    "Team": "St. Louis Blues*",
    "GP": 82,
    "W": 37,
    "L": 32,
    "T": 13,
    "OL": "",
    "PTS": 87,
    "PTS%": 0.53,
    "SRS": 0.29,
    "SOS": -0.05,
    "Finish": "2nd",
    "Playoffs": "Lost NHL Conference Semi-Finals",
    "Coaches": "J. Quenneville (37-32-13)"
  },
  {
    "Season": "1997-98",
    "Lg": "NHL",
    "Team": "St. Louis Blues*",
    "GP": 82,
    "W": 45,
    "L": 29,
    "T": 8,
    "OL": "",
    "PTS": 98,
    "PTS%": 0.598,
    "SRS": 0.63,
    "SOS": 0,
    "Finish": "3rd",
    "Playoffs": "Lost NHL Conference Semi-Finals",
    "Coaches": "J. Quenneville (45-29-8)"
  },
  {
    "Season": "1996-97",
    "Lg": "NHL",
    "Team": "St. Louis Blues*",
    "GP": 82,
    "W": 36,
    "L": 35,
    "T": 11,
    "OL": "",
    "PTS": 83,
    "PTS%": 0.506,
    "SRS": -0.03,
    "SOS": 0.01,
    "Finish": "4th",
    "Playoffs": "Lost NHL Conference Quarter-Finals",
    "Coaches": "M. Keenan (15-17-1) J. Roberts (3-3-3) J. Quenneville (18-15-7)"
  },
  {
    "Season": "1995-96",
    "Lg": "NHL",
    "Team": "St. Louis Blues*",
    "GP": 82,
    "W": 32,
    "L": 34,
    "T": 16,
    "OL": "",
    "PTS": 80,
    "PTS%": 0.488,
    "SRS": -0.35,
    "SOS": 0,
    "Finish": "4th",
    "Playoffs": "Lost NHL Conference Semi-Finals",
    "Coaches": "M. Keenan (32-34-16)"
  },
  {
    "Season": "1994-95",
    "Lg": "NHL",
    "Team": "St. Louis Blues*",
    "GP": 48,
    "W": 28,
    "L": 15,
    "T": 5,
    "OL": "",
    "PTS": 61,
    "PTS%": 0.635,
    "SRS": 0.84,
    "SOS": -0.06,
    "Finish": "2nd",
    "Playoffs": "Lost NHL Conference Quarter-Finals",
    "Coaches": "M. Keenan (28-15-5)"
  },
  {
    "Season": "1993-94",
    "Lg": "NHL",
    "Team": "St. Louis Blues*",
    "GP": 84,
    "W": 40,
    "L": 33,
    "T": 11,
    "OL": "",
    "PTS": 91,
    "PTS%": 0.542,
    "SRS": -0.16,
    "SOS": 0,
    "Finish": "4th",
    "Playoffs": "Lost NHL Conference Quarter-Finals",
    "Coaches": "B. Berry (40-33-11)"
  },
  {
    "Season": "1992-93",
    "Lg": "NHL",
    "Team": "St. Louis Blues*",
    "GP": 84,
    "W": 37,
    "L": 36,
    "T": 11,
    "OL": "",
    "PTS": 85,
    "PTS%": 0.506,
    "SRS": 0.06,
    "SOS": 0.01,
    "Finish": "4th",
    "Playoffs": "Lost NHL Division Finals",
    "Coaches": "B. Plager (4-6-1) B. Berry (33-30-10)"
  },
  {
    "Season": "1991-92",
    "Lg": "NHL",
    "Team": "St. Louis Blues*",
    "GP": 80,
    "W": 36,
    "L": 33,
    "T": 11,
    "OL": "",
    "PTS": 83,
    "PTS%": 0.519,
    "SRS": 0.16,
    "SOS": -0.01,
    "Finish": "3rd",
    "Playoffs": "Lost NHL Division Semi-Finals",
    "Coaches": "B. Sutter (36-33-11)"
  },
  {
    "Season": "1990-91",
    "Lg": "NHL",
    "Team": "St. Louis Blues*",
    "GP": 80,
    "W": 47,
    "L": 22,
    "T": 11,
    "OL": "",
    "PTS": 105,
    "PTS%": 0.656,
    "SRS": 0.7,
    "SOS": -0.05,
    "Finish": "2nd",
    "Playoffs": "Lost NHL Division Finals",
    "Coaches": "B. Sutter (47-22-11)"
  },
  {
    "Season": "1989-90",
    "Lg": "NHL",
    "Team": "St. Louis Blues*",
    "GP": 80,
    "W": 37,
    "L": 34,
    "T": 9,
    "OL": "",
    "PTS": 83,
    "PTS%": 0.519,
    "SRS": 0.16,
    "SOS": -0.04,
    "Finish": "2nd",
    "Playoffs": "Lost NHL Division Finals",
    "Coaches": "B. Sutter (37-34-9)"
  },
  {
    "Season": "1988-89",
    "Lg": "NHL",
    "Team": "St. Louis Blues*",
    "GP": 80,
    "W": 33,
    "L": 35,
    "T": 12,
    "OL": "",
    "PTS": 78,
    "PTS%": 0.488,
    "SRS": -0.25,
    "SOS": -0.13,
    "Finish": "2nd",
    "Playoffs": "Lost NHL Division Finals",
    "Coaches": "B. Sutter (33-35-12)"
  },
  {
    "Season": "1987-88",
    "Lg": "NHL",
    "Team": "St. Louis Blues*",
    "GP": 80,
    "W": 34,
    "L": 38,
    "T": 8,
    "OL": "",
    "PTS": 76,
    "PTS%": 0.475,
    "SRS": -0.35,
    "SOS": -0.15,
    "Finish": "2nd",
    "Playoffs": "Lost NHL Division Finals",
    "Coaches": "J. Martin (34-38-8)"
  },
  {
    "Season": "1986-87",
    "Lg": "NHL",
    "Team": "St. Louis Blues*",
    "GP": 80,
    "W": 32,
    "L": 33,
    "T": 15,
    "OL": "",
    "PTS": 79,
    "PTS%": 0.494,
    "SRS": -0.22,
    "SOS": -0.07,
    "Finish": "1st",
    "Playoffs": "Lost NHL Division Semi-Finals",
    "Coaches": "J. Martin (32-33-15)"
  },
  {
    "Season": "1985-86",
    "Lg": "NHL",
    "Team": "St. Louis Blues*",
    "GP": 80,
    "W": 37,
    "L": 34,
    "T": 9,
    "OL": "",
    "PTS": 83,
    "PTS%": 0.519,
    "SRS": -0.05,
    "SOS": -0.18,
    "Finish": "3rd",
    "Playoffs": "Lost NHL Conference Finals",
    "Coaches": "J. Demers (37-34-9)"
  },
  {
    "Season": "1984-85",
    "Lg": "NHL",
    "Team": "St. Louis Blues*",
    "GP": 80,
    "W": 37,
    "L": 31,
    "T": 12,
    "OL": "",
    "PTS": 86,
    "PTS%": 0.538,
    "SRS": -0.04,
    "SOS": -0.18,
    "Finish": "1st",
    "Playoffs": "Lost NHL Division Semi-Finals",
    "Coaches": "J. Demers (37-31-12)"
  },
  {
    "Season": "1983-84",
    "Lg": "NHL",
    "Team": "St. Louis Blues*",
    "GP": 80,
    "W": 32,
    "L": 41,
    "T": 7,
    "OL": "",
    "PTS": 71,
    "PTS%": 0.444,
    "SRS": -0.41,
    "SOS": -0.12,
    "Finish": "2nd",
    "Playoffs": "Lost NHL Division Finals",
    "Coaches": "J. Demers (32-41-7)"
  },
  {
    "Season": "1982-83",
    "Lg": "NHL",
    "Team": "St. Louis Blues*",
    "GP": 80,
    "W": 25,
    "L": 40,
    "T": 15,
    "OL": "",
    "PTS": 65,
    "PTS%": 0.406,
    "SRS": -0.4,
    "SOS": -0.01,
    "Finish": "4th",
    "Playoffs": "Lost NHL Division Semi-Finals",
    "Coaches": "E. Francis (10-19-3) B. Plager (15-21-12)"
  },
  {
    "Season": "1981-82",
    "Lg": "NHL",
    "Team": "St. Louis Blues*",
    "GP": 80,
    "W": 32,
    "L": 40,
    "T": 8,
    "OL": "",
    "PTS": 72,
    "PTS%": 0.45,
    "SRS": -0.52,
    "SOS": -0.1,
    "Finish": "3rd",
    "Playoffs": "Lost NHL Division Finals",
    "Coaches": "R. Berenson (28-34-6) E. Francis (4-6-2)"
  },
  {
    "Season": "1980-81",
    "Lg": "NHL",
    "Team": "St. Louis Blues*",
    "GP": 80,
    "W": 45,
    "L": 18,
    "T": 17,
    "OL": "",
    "PTS": 107,
    "PTS%": 0.669,
    "SRS": 0.85,
    "SOS": -0.04,
    "Finish": "1st",
    "Playoffs": "Lost NHL Quarter-Finals",
    "Coaches": "R. Berenson (45-18-17)"
  },
  {
    "Season": "1979-80",
    "Lg": "NHL",
    "Team": "St. Louis Blues*",
    "GP": 80,
    "W": 34,
    "L": 34,
    "T": 12,
    "OL": "",
    "PTS": 80,
    "PTS%": 0.5,
    "SRS": -0.14,
    "SOS": 0.01,
    "Finish": "2nd",
    "Playoffs": "Lost NHL Preliminary Round",
    "Coaches": "B. Plager (7-14-3) R. Berenson (27-20-9)"
  },
  {
    "Season": "1978-79",
    "Lg": "NHL",
    "Team": "St. Louis Blues",
    "GP": 80,
    "W": 18,
    "L": 50,
    "T": 12,
    "OL": "",
    "PTS": 48,
    "PTS%": 0.3,
    "SRS": -1.29,
    "SOS": -0.05,
    "Finish": "3rd",
    "Playoffs": "",
    "Coaches": "B. Plager (18-50-12)"
  },
  {
    "Season": "1977-78",
    "Lg": "NHL",
    "Team": "St. Louis Blues",
    "GP": 80,
    "W": 20,
    "L": 47,
    "T": 13,
    "OL": "",
    "PTS": 53,
    "PTS%": 0.331,
    "SRS": -1.33,
    "SOS": 0.03,
    "Finish": "4th",
    "Playoffs": "",
    "Coaches": "L. Boivin (11-36-7) B. Plager (9-11-6)"
  },
  {
    "Season": "1976-77",
    "Lg": "NHL",
    "Team": "St. Louis Blues*",
    "GP": 80,
    "W": 32,
    "L": 39,
    "T": 9,
    "OL": "",
    "PTS": 73,
    "PTS%": 0.456,
    "SRS": -0.5,
    "SOS": -0.04,
    "Finish": "1st",
    "Playoffs": "Lost NHL Quarter-Finals",
    "Coaches": "E. Francis (32-39-9)"
  },
  {
    "Season": "1975-76",
    "Lg": "NHL",
    "Team": "St. Louis Blues*",
    "GP": 80,
    "W": 29,
    "L": 37,
    "T": 14,
    "OL": "",
    "PTS": 72,
    "PTS%": 0.45,
    "SRS": -0.54,
    "SOS": -0.03,
    "Finish": "3rd",
    "Playoffs": "Lost NHL Preliminary Round",
    "Coaches": "G. Young (9-15-5) L. Patrick (3-5-0) L. Boivin (17-17-9)"
  },
  {
    "Season": "1974-75",
    "Lg": "NHL",
    "Team": "St. Louis Blues*",
    "GP": 80,
    "W": 35,
    "L": 31,
    "T": 14,
    "OL": "",
    "PTS": 84,
    "PTS%": 0.525,
    "SRS": -0.01,
    "SOS": -0.04,
    "Finish": "2nd",
    "Playoffs": "Lost NHL Preliminary Round",
    "Coaches": "L. Angotti (2-5-2) L. Patrick (1-0-1) G. Young (32-26-11)"
  },
  {
    "Season": "1973-74",
    "Lg": "NHL",
    "Team": "St. Louis Blues",
    "GP": 78,
    "W": 26,
    "L": 40,
    "T": 12,
    "OL": "",
    "PTS": 64,
    "PTS%": 0.41,
    "SRS": -0.52,
    "SOS": 0.02,
    "Finish": "6th",
    "Playoffs": "",
    "Coaches": "J. Talbot (22-25-8) L. Angotti (4-15-4)"
  },
  {
    "Season": "1972-73",
    "Lg": "NHL",
    "Team": "St. Louis Blues*",
    "GP": 78,
    "W": 32,
    "L": 34,
    "T": 12,
    "OL": "",
    "PTS": 76,
    "PTS%": 0.487,
    "SRS": -0.21,
    "SOS": 0.02,
    "Finish": "4th",
    "Playoffs": "Lost NHL Quarter-Finals",
    "Coaches": "A. Arbour (2-6-5) J. Talbot (30-28-7)"
  },
  {
    "Season": "1971-72",
    "Lg": "NHL",
    "Team": "St. Louis Blues*",
    "GP": 78,
    "W": 28,
    "L": 39,
    "T": 11,
    "OL": "",
    "PTS": 67,
    "PTS%": 0.429,
    "SRS": -0.46,
    "SOS": 0.04,
    "Finish": "3rd",
    "Playoffs": "Lost NHL Semi-Finals",
    "Coaches": "S. Abel (3-6-1) B. McCreary (6-14-4) A. Arbour (19-19-6)"
  },
  {
    "Season": "1970-71",
    "Lg": "NHL",
    "Team": "St. Louis Blues*",
    "GP": 78,
    "W": 34,
    "L": 25,
    "T": 19,
    "OL": "",
    "PTS": 87,
    "PTS%": 0.558,
    "SRS": 0.18,
    "SOS": -0.01,
    "Finish": "2nd",
    "Playoffs": "Lost NHL Quarter-Finals",
    "Coaches": "A. Arbour (21-15-14) S. Bowman (13-10-5)"
  },
  {
    "Season": "1969-70",
    "Lg": "NHL",
    "Team": "St. Louis Blues*",
    "GP": 76,
    "W": 37,
    "L": 27,
    "T": 12,
    "OL": "",
    "PTS": 86,
    "PTS%": 0.566,
    "SRS": 0.45,
    "SOS": -0.15,
    "Finish": "1st",
    "Playoffs": "Lost Stanley Cup Final",
    "Coaches": "S. Bowman (37-27-12)"
  },
  {
    "Season": "1968-69",
    "Lg": "NHL",
    "Team": "St. Louis Blues*",
    "GP": 76,
    "W": 37,
    "L": 25,
    "T": 14,
    "OL": "",
    "PTS": 88,
    "PTS%": 0.579,
    "SRS": 0.48,
    "SOS": -0.14,
    "Finish": "1st",
    "Playoffs": "Lost Stanley Cup Final",
    "Coaches": "S. Bowman (37-25-14)"
  },
  {
    "Season": "1967-68",
    "Lg": "NHL",
    "Team": "St. Louis Blues*",
    "GP": 74,
    "W": 27,
    "L": 31,
    "T": 16,
    "OL": "",
    "PTS": 70,
    "PTS%": 0.473,
    "SRS": -0.41,
    "SOS": -0.23,
    "Finish": "3rd",
    "Playoffs": "Lost Stanley Cup Final",
    "Coaches": "L. Patrick (4-10-2) S. Bowman (23-21-14)"
  }
]